vpython-7.6.5.dist-info/RECORD
vpython-7.6.5.dist-info/METADATA
vpython-7.6.5.dist-info/WHEEL
vpython-7.6.5.dist-info/top_level.txt
vpython-7.6.5.dist-info/LICENSE.txt
vpython/__init__.py
vpython/vpython.py
vpython/_vector_import_helper.py
vpython/shapespaths.py
vpython/rate_control.py
vpython/gs_version.py
vpython/_notebook_helpers.py
vpython/qtbrowser.py
vpython/vector.py
vpython/with_notebook.py
vpython/cyvector.cpython-310-x86_64-linux-gnu.so
vpython/no_notebook.py
vpython/vpython_data/stones_bumpmap.jpg
vpython/vpython_data/stucco_texture.jpg
vpython/vpython_data/stones_texture.jpg
vpython/vpython_data/flower_texture.jpg
vpython/vpython_data/gravel_bumpmap.jpg
vpython/vpython_data/rough_texture.jpg
vpython/vpython_data/stucco_bumpmap.jpg
vpython/vpython_data/gravel_texture.jpg
vpython/vpython_data/rock_bumpmap.jpg
vpython/vpython_data/granite_texture.jpg
vpython/vpython_data/wood_old_texture.jpg
vpython/vpython_data/rug_texture.jpg
vpython/vpython_data/favicon.ico
vpython/vpython_data/earth_texture.jpg
vpython/vpython_data/rock_texture.jpg
vpython/vpython_data/metal_texture.jpg
vpython/vpython_data/wood_texture.jpg
vpython/vpython_data/wood_old_bumpmap.jpg
vpython/vpython_data/Roboto-Medium.ttf
vpython/vpython_data/NimbusRomNo9L-Med.otf
vpython/vpython_libraries/plotly.min.js
vpython/vpython_libraries/glow.min.js
vpython/vpython_libraries/glowcomm.js
vpython/vpython_libraries/jquery-ui.custom.css
vpython/vpython_libraries/jquery-ui.custom.min.js
vpython/vpython_libraries/glowcomm.html
vpython/vpython_libraries/ide.css
vpython/vpython_libraries/jquery.min.js
vpython/vpython_libraries/images/ui-icons_469bdd_256x240.png
vpython/vpython_libraries/images/ui-icons_f9bd01_256x240.png
vpython/vpython_libraries/images/ui-icons_217bc0_256x240.png
vpython/vpython_libraries/images/ui-bg_glass_95_fef1ec_1x400.png
vpython/vpython_libraries/images/ui-icons_d8e7f3_256x240.png
vpython/vpython_libraries/images/ui-bg_inset-hard_100_f5f8f9_1x100.png
vpython/vpython_libraries/images/animated-overlay.gif
vpython/vpython_libraries/images/ui-bg_flat_55_fbec88_40x100.png
