Metadata-Version: 2.1
Name: vpython
Version: 7.6.5
Summary: VPython for Jupyter Notebook
Home-page: http://pypi.python.org/pypi/vpython/
Author: John Coady / Ruth Chabay / Bruce Sherwood / Steve Spicklemire
Author-email: bruce.sherwood@gmail.com
License: LICENSE.txt
Keywords: vpython
Classifier: Framework :: IPython
Classifier: Development Status :: 5 - Production/Stable
Classifier: Environment :: Web Environment
Classifier: Intended Audience :: End Users/Desktop
Classifier: Natural Language :: English
Classifier: Programming Language :: Python
Classifier: Topic :: Multimedia :: Graphics :: 3D Modeling
Classifier: Topic :: Multimedia :: Graphics :: 3D Rendering
Classifier: Topic :: Scientific/Engineering :: Visualization
Requires-Python: >=3.7
License-File: LICENSE.txt
Requires-Dist: jupyter
Requires-Dist: jupyter-server-proxy
Requires-Dist: jupyterlab-vpython>=3.1.8
Requires-Dist: numpy
Requires-Dist: ipykernel
Requires-Dist: autobahn<27,>=22.6.1
